pyavrophonetic/__init__.py
pyavrophonetic/avro.py
pyavrophonetic/config.py
pyavrophonetic/resources/avrodict.json
pyavrophonetic/utils/__init__.py
pyavrophonetic/utils/count.py
pyavrophonetic/utils/validate.py
pyconvq/__init__.py
pyconvq/conv.py
pyconvq-0.1.7.dist-info/DESCRIPTION.rst
pyconvq-0.1.7.dist-info/METADATA
pyconvq-0.1.7.dist-info/RECORD
pyconvq-0.1.7.dist-info/WHEEL
pyconvq-0.1.7.dist-info/metadata.json
pyconvq-0.1.7.dist-info/top_level.txt
