Metadata-Version: 2.0
Name: pyconvq
Version: 0.1.7
Summary: Query expander using azure and avro
Home-page: UNKNOWN
Author: Nafis Ahmed
Author-email: nafis@algomatrix.co
License: MIT
Platform: UNKNOWN
Requires-Dist: mstranslator (==0.3.2)
Requires-Dist: redislite (==3.2.311)
Requires-Dist: simplejson (==3.12.0)
